ipc_sync-0.1.0.post1.dist-info/METADATA
ipc_sync-0.1.0.post1.dist-info/WHEEL
ipc_sync-0.1.0.post1.dist-info/entry_points.txt
ipc_sync-0.1.0.post1.dist-info/licenses/LICENSE
ipc_sync/__init__.py
ipc_sync/_base.py
ipc_sync/_env.py
ipc_sync/_posix.py
ipc_sync/_win.py
ipc_sync-0.1.0.post1.dist-info/RECORD
