Metadata-Version: 2.1
Name: ipc-sync
Version: 0.1.0.post1
Summary: Cross-platform utils for IPC (inter-processing communication) synchronization in Python
Keywords: IPC,cross-platform
Author-Email: monchin <pazzinter@126.com>
License: MIT
Classifier: Topic :: Utilities
Classifier: Programming Language :: Python :: 3
Classifier: Programming Language :: Python :: 3.8
Classifier: Programming Language :: Python :: 3.9
Classifier: Programming Language :: Python :: 3.10
Classifier: Programming Language :: Python :: 3.11
Classifier: Programming Language :: Python :: 3.12
Classifier: Programming Language :: Python :: 3.13
Project-URL: Homepage, https://github.com/monchin/ipc-sync
Project-URL: Repository, https://github.com/monchin/ipc-sync
Requires-Python: >=3.8
Requires-Dist: pywin32>=308; sys_platform == "win32"
